nonebot_api_paddle/__init__.py
nonebot_api_paddle/api_excel.py
nonebot_api_paddle/api_ocr.py
nonebot_api_paddle/api_voice.py
nonebot_api_paddle-1.0.3.dist-info/LICENSE.txt
nonebot_api_paddle-1.0.3.dist-info/METADATA
nonebot_api_paddle-1.0.3.dist-info/WHEEL
nonebot_api_paddle-1.0.3.dist-info/top_level.txt
nonebot_api_paddle-1.0.3.dist-info/RECORD
