Metadata-Version: 2.1
Name: nonebot-api-paddle
Version: 1.0.3
Summary: nonbot_api_paddle
Home-page: https://github.com/canxin121/nonebot_api_paddle
Author: canxin
Author-email: 1969730106@qq.com
Classifier: Programming Language :: Python :: 3.10
Classifier: Programming Language :: Python :: 3.8
Classifier: License :: OSI Approved :: GNU Affero General Public License v3
Classifier: Operating System :: OS Independent
License-File: LICENSE.txt
Requires-Dist: nonebot2 (>=2.0.0rc3)
Requires-Dist: nonebot-adapter-onebot (>=2.0.0b1)
Requires-Dist: requests (>=2.28.2)
Requires-Dist: ffmpeg (>=1.4)
Requires-Dist: pydantic (>=1.10.6)
Requires-Dist: Pillow (>=9.5.0)
Requires-Dist: pandas (>=1.5.3)
Requires-Dist: openpyxl (>=3.1.2)
